virnatrap/__init__.py
virnatrap/command_line.py
virnatrap/virnatrap.py
virnatrap-1.0.dist-info/LICENSE
virnatrap-1.0.dist-info/METADATA
virnatrap-1.0.dist-info/WHEEL
virnatrap-1.0.dist-info/entry_points.txt
virnatrap-1.0.dist-info/top_level.txt
virnatrap-1.0.dist-info/RECORD
