Metadata-Version: 2.1
Name: virnatrap
Version: 1.0
Summary: Extract viral contigs
Author: Add list
Author-email: aelbasir@wistar.org, nauslander@wistar.org
License: UNKNOWN
Platform: UNKNOWN
Classifier: Programming Language :: Python :: 3
Classifier: License :: OSI Approved :: GNU General Public License (GPL)
Classifier: Operating System :: OS Independent
Requires-Python: >=3.6
License-File: LICENSE
Requires-Dist: numpy (>=1.17.3)
Requires-Dist: tensorflow (>=2.0.0)
Requires-Dist: argparse
